counter.sv
module counter #(
    parameter WIDTH = 8

)
(
    // interface signals
    input   logic             clk, //clock
    input   logic             rst,//reset 
    input   logic             en,
    output  logic [WIDTH-1:0] count
);

always_ff @(posedge clk)
 begin
    if(rst ) count <= {WIDTH{1'b0}};
    else     count <= count + {{WIDTH-1{1'b0}},en};
    
end
    
endmodule

count.vcd
$version Generated by VerilatedVcd $end
$date Thu Oct 27 11:07:31 2022 $end
$timescale 1ps $end

 $scope module TOP $end
  $var wire  1 # clk $end
  $var wire  8 & count [7:0] $end
  $var wire  1 % en $end
  $var wire  1 $ rst $end
  $scope module counter $end
   $var wire 32 ' WIDTH [31:0] $end
   $var wire  1 # clk $end
   $var wire  8 & count [7:0] $end
   $var wire  1 % en $end
   $var wire  1 $ rst $end
  $upscope $end
 $upscope $end
$enddefinitions $end


#0
1#
1$
0%
b00000000 &
b00000000000000000000000000001000 '
#1
0#
#2
1#
#3
0#
#4
1#
#5
0#
#6
1#
0$
#7
0#
#8
1#
#9
0#
#10
1#
#11
0#
#12
1#
#13
0#
#14
1#
#15
0#
#16
1#
#17
0#
#18
1#
#19
0#
#20
1#
#21
0#
#22
1#
#23
0#
#24
1#
#25
0#
#26
1#
#27
0#
#28
1#
#29
0#
#30
1#
#31
0#
#32
1#
1$
#33
0#
#34
1#
0$
#35
0#
#36
1#
#37
0#
#38
1#
#39
0#
#40
1#
#41
0#
#42
1#
#43
0#
#44
1#
#45
0#
#46
1#
#47
0#
#48
1#
#49
0#
#50
1#
#51
0#
#52
1#
#53
0#
#54
1#
#55
0#
#56
1#
#57
0#
#58
1#
#59
0#
#60
1#
#61
0#
#62
1#
#63
0#
#64
1#
#65
0#
#66
1#
#67
0#
#68
1#
#69
0#
#70
1#
#71
0#
#72
1#
#73
0#
#74
1#
#75
0#
#76
1#
#77
0#
#78
1#
#79
0#
#80
1#
#81
0#
#82
1#
#83
0#
#84
1#
#85
0#
#86
1#
#87
0#
#88
1#
#89
0#
#90
1#
#91
0#
#92
1#
#93
0#
#94
1#
#95
0#
#96
1#
#97
0#
#98
1#
#99
0#
#100
1#
#101
0#
#102
1#
#103
0#
#104
1#
#105
0#
#106
1#
#107
0#
#108
1#
#109
0#
#110
1#
#111
0#
#112
1#
#113
0#
#114
1#
#115
0#
#116
1#
#117
0#
#118
1#
#119
0#
#120
1#
#121
0#
#122
1#
#123
0#
#124
1#
#125
0#
#126
1#
#127
0#
#128
1#
#129
0#
#130
1#
#131
0#
#132
1#
#133
0#
#134
1#
#135
0#
#136
1#
#137
0#
#138
1#
#139
0#
#140
1#
#141
0#
#142
1#
#143
0#
#144
1#
#145
0#
#146
1#
#147
0#
#148
1#
#149
0#
#150
1#
#151
0#
#152
1#
#153
0#
#154
1#
#155
0#
#156
1#
#157
0#
#158
1#
#159
0#
#160
1#
#161
0#
#162
1#
#163
0#
#164
1#
#165
0#
#166
1#
#167
0#
#168
1#
#169
0#
#170
1#
#171
0#
#172
1#
#173
0#
#174
1#
#175
0#
#176
1#
#177
0#
#178
1#
#179
0#
#180
1#
#181
0#
#182
1#
#183
0#
#184
1#
#185
0#
#186
1#
#187
0#
#188
1#
#189
0#
#190
1#
#191
0#
#192
1#
#193
0#
#194
1#
#195
0#
#196
1#
#197
0#
#198
1#
#199
0#
#200
1#
1%
#201
0#
#202
1#
b00000001 &
#203
0#
#204
1#
b00000010 &
#205
0#
#206
1#
b00000011 &
#207
0#
#208
1#
b00000100 &
#209
0#
#210
1#
b00000101 &
#211
0#
#212
1#
b00000110 &
#213
0#
#214
1#
b00000111 &
#215
0#
#216
1#
b00001000 &
#217
0#
#218
1#
b00001001 &
#219
0#
#220
1#
b00001010 &
#221
0#
#222
1#
b00001011 &
#223
0#
#224
1#
b00001100 &
#225
0#
#226
1#
b00001101 &
#227
0#
#228
1#
b00001110 &
#229
0#
#230
1#
b00001111 &
#231
0#
#232
1#
b00010000 &
#233
0#
#234
1#
b00010001 &
#235
0#
#236
1#
b00010010 &
#237
0#
#238
1#
b00010011 &
#239
0#
#240
1#
b00010100 &
#241
0#
#242
1#
b00010101 &
#243
0#
#244
1#
b00010110 &
#245
0#
#246
1#
b00010111 &
#247
0#
#248
1#
b00011000 &
#249
0#
#250
1#
b00011001 &
#251
0#
#252
1#
b00011010 &
#253
0#
#254
1#
b00011011 &
#255
0#
#256
1#
b00011100 &
#257
0#
#258
1#
b00011101 &
#259
0#
#260
1#
b00011110 &
#261
0#
#262
1#
b00011111 &
#263
0#
#264
1#
b00100000 &
#265
0#
#266
1#
b00100001 &
#267
0#
#268
1#
b00100010 &
#269
0#
#270
1#
b00100011 &
#271
0#
#272
1#
b00100100 &
#273
0#
#274
1#
b00100101 &
#275
0#
#276
1#
b00100110 &
#277
0#
#278
1#
b00100111 &
#279
0#
#280
1#
b00101000 &
#281
0#
#282
1#
b00101001 &
#283
0#
#284
1#
b00101010 &
#285
0#
#286
1#
b00101011 &
#287
0#
#288
1#
b00101100 &
#289
0#
#290
1#
b00101101 &
#291
0#
#292
1#
b00101110 &
#293
0#
#294
1#
b00101111 &
#295
0#
#296
1#
b00110000 &
#297
0#
#298
1#
b00110001 &
#299
0#
#300
1#
b00110010 &
#301
0#
#302
1#
b00110011 &
#303
0#
#304
1#
b00110100 &
#305
0#
#306
1#
b00110101 &
#307
0#
#308
1#
b00110110 &
#309
0#
#310
1#
b00110111 &
#311
0#
#312
1#
b00111000 &
#313
0#
#314
1#
b00111001 &
#315
0#
#316
1#
b00111010 &
#317
0#
#318
1#
b00111011 &
#319
0#
#320
1#
b00111100 &
#321
0#
#322
1#
b00111101 &
#323
0#
#324
1#
b00111110 &
#325
0#
#326
1#
b00111111 &
#327
0#
#328
1#
b01000000 &
#329
0#
#330
1#
b01000001 &
#331
0#
#332
1#
b01000010 &
#333
0#
#334
1#
b01000011 &
#335
0#
#336
1#
b01000100 &
#337
0#
#338
1#
b01000101 &
#339
0#
#340
1#
b01000110 &
#341
0#
#342
1#
b01000111 &
#343
0#
#344
1#
b01001000 &
#345
0#
#346
1#
b01001001 &
#347
0#
#348
1#
b01001010 &
#349
0#
#350
1#
b01001011 &
#351
0#
#352
1#
b01001100 &
#353
0#
#354
1#
b01001101 &
#355
0#
#356
1#
b01001110 &
#357
0#
#358
1#
b01001111 &
#359
0#
#360
1#
b01010000 &
#361
0#
#362
1#
b01010001 &
#363
0#
#364
1#
b01010010 &
#365
0#
#366
1#
b01010011 &
#367
0#
#368
1#
b01010100 &
#369
0#
#370
1#
b01010101 &
#371
0#
#372
1#
b01010110 &
#373
0#
#374
1#
b01010111 &
#375
0#
#376
1#
b01011000 &
#377
0#
#378
1#
b01011001 &
#379
0#
#380
1#
b01011010 &
#381
0#
#382
1#
b01011011 &
#383
0#
#384
1#
b01011100 &
#385
0#
#386
1#
b01011101 &
#387
0#
#388
1#
b01011110 &
#389
0#
#390
1#
b01011111 &
#391
0#
#392
1#
b01100000 &
#393
0#
#394
1#
b01100001 &
#395
0#
#396
1#
b01100010 &
#397
0#
#398
1#
b01100011 &
#399
0#
#400
1#
b01100100 &
#401
0#
#402
1#
b01100101 &
#403
0#
#404
1#
b01100110 &
#405
0#
#406
1#
b01100111 &
#407
0#
#408
1#
b01101000 &
#409
0#
#410
1#
0%
b01101001 &
